iai_common/__init__.py
iai_common/communications/__init__.py
iai_common/communications/utils.py
iai_common/communications/isp/Action.py
iai_common/communications/isp/BoundingBox.py
iai_common/communications/isp/ClientHandshake.py
iai_common/communications/isp/Command.py
iai_common/communications/isp/Dict.py
iai_common/communications/isp/ForwardGears.py
iai_common/communications/isp/Info.py
iai_common/communications/isp/Initialize.py
iai_common/communications/isp/Location.py
iai_common/communications/isp/Message.py
iai_common/communications/isp/MessageBody.py
iai_common/communications/isp/Obs.py
iai_common/communications/isp/Resolution.py
iai_common/communications/isp/Rotation.py
iai_common/communications/isp/ScenarioParameters.py
iai_common/communications/isp/Sensor.py
iai_common/communications/isp/SensorData.py
iai_common/communications/isp/SensorsDataDict.py
iai_common/communications/isp/SensorsDict.py
iai_common/communications/isp/ServerHandshake.py
iai_common/communications/isp/State.py
iai_common/communications/isp/Step.py
iai_common/communications/isp/Tensor.py
iai_common/communications/isp/VehiclePhysics.py
iai_common/communications/isp/WheelPhysics.py
iai_common/communications/isp/WorldParameters.py
iai_common/communications/isp/__init__.py
iai_common-1.0.3.dist-info/LICENSE
iai_common-1.0.3.dist-info/METADATA
iai_common-1.0.3.dist-info/WHEEL
iai_common-1.0.3.dist-info/top_level.txt
iai_common-1.0.3.dist-info/RECORD
