Metadata-Version: 2.1
Name: iai-common
Version: 1.0.3
Summary: Common shared libraries for IAI Product interfaces
Author: InvertedAI
Author-email: alireza.morsali@inverted.ai
License: UNKNOWN
Platform: UNKNOWN
Classifier: Programming Language :: Python :: 3
Classifier: License :: OSI Approved :: MIT License
Classifier: Operating System :: OS Independent
Requires-Python: >=3.7
License-File: LICENSE
Requires-Dist: torch (==1.11.0)
Requires-Dist: opencv-python (==4.5.5.64)
Requires-Dist: flatbuffers (==2.0)
